lzhaiofetcher/__init__.py
lzhaiofetcher/fetcher.py
lzhaiofetcher-1.1.dist-info/METADATA
lzhaiofetcher-1.1.dist-info/WHEEL
lzhaiofetcher-1.1.dist-info/top_level.txt
lzhaiofetcher-1.1.dist-info/RECORD
