Metadata-Version: 2.4
Name: lzhaiofetcher
Version: 1.1
Summary: 将 aiohttp 的异步 get 封装了 3 个函数。包含失败重试、串行任务、并行任务、随机延迟、任务并发数控制等特性
Author-email: lzh <zhhtdm@hotmail.com>
License: MIT
Project-URL: Homepage, https://github.com/zhhtdm/aio-fetcher
Project-URL: Repository, https://github.com/zhhtdm/aio-fetcher
Requires-Python: >=3.7
Requires-Dist: aiohttp
Requires-Dist: lzhgetlogger
